exasol_udf_mock_python/__init__.py
exasol_udf_mock_python/column.py
exasol_udf_mock_python/connection.py
exasol_udf_mock_python/group.py
exasol_udf_mock_python/mock_context.py
exasol_udf_mock_python/mock_context_run_wrapper.py
exasol_udf_mock_python/mock_exa_environment.py
exasol_udf_mock_python/mock_meta_data.py
exasol_udf_mock_python/udf_context.py
exasol_udf_mock_python/udf_mock_executor.py
exasol_udf_mock_python-0.5.0.dist-info/LICENSE
exasol_udf_mock_python-0.5.0.dist-info/METADATA
exasol_udf_mock_python-0.5.0.dist-info/WHEEL
exasol_udf_mock_python-0.5.0.dist-info/RECORD
