Metadata-Version: 2.3
Name: exasol-udf-mock-python
Version: 0.5.0
Summary: Mocking framework for Exasol Python UDFs
License: MIT
Keywords: exasol,udf,mock,testing
Author: Torsten Kilias
Author-email: torsten.kilias@exasol.com
Requires-Python: >=3.10.0,<4.0
Classifier: License :: OSI Approved :: MIT License
Classifier: Programming Language :: Python :: 3
Classifier: Programming Language :: Python :: 3.10
Classifier: Programming Language :: Python :: 3.11
Classifier: Programming Language :: Python :: 3.12
Classifier: Programming Language :: Python :: 3.13
Requires-Dist: numpy (>=1.26.4,<3)
Requires-Dist: pandas (>=2.2.3,<3.0.0)
Project-URL: Homepage, https://github.com/exasol/udf-mock-python
Project-URL: Repository, https://github.com/exasol/udf-mock-python
